README.txt
setup.py
djangocms_utils/__init__.py
djangocms_utils/admin.py
djangocms_utils/fields.py
djangocms_utils/models.py
djangocms_utils/tests.py
djangocms_utils.egg-info/PKG-INFO
djangocms_utils.egg-info/SOURCES.txt
djangocms_utils.egg-info/dependency_links.txt
djangocms_utils.egg-info/top_level.txt
djangocms_utils/templatetags/__init__.py
djangocms_utils/templatetags/djangocms_utils_tags.py