Metadata-Version: 1.0
Name: djangocms-utils
Version: 0.9.5
Summary: Utilities for django-cms
Home-page: http://github.com/fivethreeo/djangocms-utils/
Author: Oyvind Saltvik
Author-email: oyvind.saltvik@gmail.com
License: UNKNOWN
Platform: UNKNOWN
